c_two/__init__.py
c_two/cli.py
c_two/error.py
c_two/compo/__init__.py
c_two/compo/runtime_connect.py
c_two/crm/__init__.py
c_two/crm/meta.py
c_two/crm/template.py
c_two/mcp/__init__.py
c_two/mcp/mcp_util.py
c_two/rpc/__init__.py
c_two/rpc/client.py
c_two/rpc/routing.py
c_two/rpc/server.py
c_two/rpc/transferable.py
c_two/rpc/base/__init__.py
c_two/rpc/base/base_client.py
c_two/rpc/base/base_server.py
c_two/rpc/event/__init__.py
c_two/rpc/event/event.py
c_two/rpc/event/event_queue.py
c_two/rpc/http/__init__.py
c_two/rpc/http/http_client.py
c_two/rpc/http/http_server.py
c_two/rpc/memory/__init__.py
c_two/rpc/memory/memory_client.py
c_two/rpc/memory/memory_routing.py
c_two/rpc/memory/memory_server.py
c_two/rpc/thread/__init__.py
c_two/rpc/thread/thread_client.py
c_two/rpc/thread/thread_server.py
c_two/rpc/util/__init__.py
c_two/rpc/util/encoding.py
c_two/rpc/util/wait.py
c_two/rpc/zmq/__init__.py
c_two/rpc/zmq/zmq_client.py
c_two/rpc/zmq/zmq_server.py
c_two/seed/__init__.py
c_two/seed/docker_builder.py
c_two-0.2.6.dist-info/licenses/LICENSE
c_two-0.2.6.dist-info/METADATA
c_two-0.2.6.dist-info/WHEEL
c_two-0.2.6.dist-info/entry_points.txt
c_two-0.2.6.dist-info/top_level.txt
c_two-0.2.6.dist-info/RECORD
