Metadata-Version: 2.4
Name: c-two
Version: 0.2.6
Summary: C-Two is a resource-RPC framework that enables resource-oriented classes to be remotely invoked across different processes or machines.
Requires-Python: >=3.10
License-File: LICENSE
Requires-Dist: click>=8.2.1
Requires-Dist: docker>=7.1.0
Requires-Dist: httpx>=0.28.1
Requires-Dist: mcp[cli]>=1.6.0
Requires-Dist: pyzmq>=27.0.0
Requires-Dist: requests>=2.32.4
Requires-Dist: starlette>=0.46.0
Requires-Dist: watchdog>=6.0.0
Dynamic: license-file
